{
    "Ar36": {
        "error": 0.00018951410987170744, 
        "filter_outliers_dict": {
            "filter_outliers": true, 
            "iterations": 1, 
            "std_devs": 2
        }, 
        "fit": "Parabolic", 
        "value": 0.009813327435377387
    }, 
    "Ar37": {
        "error": 0.003528984854597122, 
        "filter_outliers_dict": {
            "filter_outliers": true, 
            "iterations": 1, 
            "std_devs": 2
        }, 
        "fit": "linear", 
        "value": 0.007011623225615162
    }, 
    "Ar38": {
        "error": 0.001674790554341639, 
        "filter_outliers_dict": {
            "filter_outliers": true, 
            "iterations": 1, 
            "std_devs": 2
        }, 
        "fit": "linear", 
        "value": -0.017106357614930463
    }, 
    "Ar39": {
        "error": 0.007056612100815434, 
        "filter_outliers_dict": {
            "filter_outliers": true, 
            "iterations": 1, 
            "std_devs": 2
        }, 
        "fit": "Parabolic", 
        "value": 0.33715981032094877
    }, 
    "Ar40": {
        "error": 0.006101348816296393, 
        "filter_outliers_dict": {
            "filter_outliers": true, 
            "iterations": 1, 
            "std_devs": 2
        }, 
        "fit": "Parabolic", 
        "value": 2.766027930117905
    }, 
    "Ar41": {
        "error": 0.004243000347399917, 
        "filter_outliers_dict": {
            "filter_outliers": true, 
            "iterations": 1, 
            "std_devs": 2
        }, 
        "fit": "linear", 
        "value": -0.14460087070328254
    }
}