{
    "Ar36": {
        "error": 0.00018099411682202598, 
        "filter_outliers_dict": {
            "filter_outliers": true, 
            "iterations": 1, 
            "std_devs": 2
        }, 
        "fit": "Parabolic", 
        "value": 0.008183822186393113
    }, 
    "Ar37": {
        "error": 0.0038094657977219104, 
        "filter_outliers_dict": {
            "filter_outliers": true, 
            "iterations": 1, 
            "std_devs": 2
        }, 
        "fit": "linear", 
        "value": 0.010573066365585082
    }, 
    "Ar38": {
        "error": 0.001698433756286796, 
        "filter_outliers_dict": {
            "filter_outliers": true, 
            "iterations": 1, 
            "std_devs": 2
        }, 
        "fit": "linear", 
        "value": -0.0031098973108905164
    }, 
    "Ar39": {
        "error": 0.0069233045587309165, 
        "filter_outliers_dict": {
            "filter_outliers": true, 
            "iterations": 1, 
            "std_devs": 2
        }, 
        "fit": "Parabolic", 
        "value": 0.06170244862075459
    }, 
    "Ar40": {
        "error": 0.00593284954595498, 
        "filter_outliers_dict": {
            "filter_outliers": true, 
            "iterations": 1, 
            "std_devs": 2
        }, 
        "fit": "Parabolic", 
        "value": 0.6767305421192137
    }, 
    "Ar41": {
        "error": 0.003748344743374267, 
        "filter_outliers_dict": {
            "filter_outliers": true, 
            "iterations": 1, 
            "std_devs": 2
        }, 
        "fit": "linear", 
        "value": -0.1479585639861432
    }
}