{
    "AX": {
        "error": 0.004536275442277012,
        "error_type": "SEM",
        "filter_outliers_dict": {
            "filter_outliers": true,
            "iterations": 1,
            "std_devs": 2
        },
        "fit": "Average",
        "fn": 114,
        "include_baseline_error": false,
        "n": 120,
        "reviewed": true,
        "value": 0.014517185757428882
    },
    "CDD": {
        "error": 2.7827744695905364e-06,
        "error_type": "SEM",
        "filter_outliers_dict": {
            "filter_outliers": true,
            "iterations": 1,
            "std_devs": 10
        },
        "fit": "Average",
        "fn": 120,
        "include_baseline_error": false,
        "n": 120,
        "reviewed": true,
        "value": 6.32976480119396e-06
    },
    "H1": {
        "error": 0.003201031486590869,
        "error_type": "SEM",
        "filter_outliers_dict": {
            "filter_outliers": true,
            "iterations": 1,
            "std_devs": 2
        },
        "fit": "Average",
        "fn": 114,
        "include_baseline_error": false,
        "n": 120,
        "reviewed": true,
        "value": 0.016778449858783892
    },
    "H2": {
        "error": 0.00985157,
        "error_type": "SEM",
        "filter_outliers_dict": {
            "filter_outliers": true,
            "iterations": 1,
            "std_devs": 2
        },
        "fit": "average",
        "value": 0.0417392507
    },
    "L1": {
        "error": 0.0018722504359191823,
        "error_type": "SEM",
        "filter_outliers_dict": {
            "filter_outliers": true,
            "iterations": 1,
            "std_devs": 2
        },
        "fit": "Average",
        "fn": 114,
        "include_baseline_error": false,
        "n": 120,
        "reviewed": true,
        "value": -0.04573200283196281
    },
    "L2": {
        "error": 0.0036194911937053285,
        "error_type": "SEM",
        "filter_outliers_dict": {
            "filter_outliers": true,
            "iterations": 1,
            "std_devs": 2
        },
        "fit": "Average",
        "fn": 113,
        "include_baseline_error": false,
        "n": 120,
        "reviewed": true,
        "value": -0.04224982071533723
    }
}