{
    "AX": {
        "error": 0.003972796989666391,
        "filter_outliers_dict": {
            "filter_outliers": true,
            "iterations": 1,
            "std_devs": 2
        },
        "fit": "Average",
        "fn": 175,
        "include_baseline_error": false,
        "n": 180,
        "reviewed": true,
        "value": -0.043265823034702666
    },
    "CDD": {
        "error": 3.5064381907754195e-06,
        "filter_outliers_dict": {
            "filter_outliers": true,
            "iterations": 1,
            "std_devs": 10
        },
        "fit": "Average",
        "fn": 180,
        "include_baseline_error": false,
        "n": 180,
        "reviewed": true,
        "value": 1.4753438881598413e-05
    },
    "H1": {
        "error": 0.0031757879722005985,
        "filter_outliers_dict": {
            "filter_outliers": true,
            "iterations": 1,
            "std_devs": 2
        },
        "fit": "Average",
        "fn": 175,
        "include_baseline_error": false,
        "n": 180,
        "reviewed": true,
        "value": -0.03548794252840578
    },
    "H2": {
        "error": 0.0029858883981071075,
        "filter_outliers_dict": {
            "filter_outliers": true,
            "iterations": 1,
            "std_devs": 2
        },
        "fit": "average",
        "value": -0.17722403825661662
    },
    "L1": {
        "error": 0.0014704594682382738,
        "filter_outliers_dict": {
            "filter_outliers": true,
            "iterations": 1,
            "std_devs": 2
        },
        "fit": "Average",
        "fn": 170,
        "include_baseline_error": false,
        "n": 180,
        "reviewed": true,
        "value": -0.02287577777135405
    },
    "L2": {
        "error": 0.003634104160174858,
        "filter_outliers_dict": {
            "filter_outliers": true,
            "iterations": 1,
            "std_devs": 2
        },
        "fit": "Average",
        "fn": 170,
        "include_baseline_error": false,
        "n": 180,
        "reviewed": true,
        "value": -0.020984887250404642
    }
}