{
    "AX": {
        "error": 0.004022628033920214, 
        "filter_outliers_dict": {
            "filter_outliers": true, 
            "iterations": 1, 
            "std_devs": 2
        }, 
        "fit": "average", 
        "value": -0.03634531510906684
    }, 
    "CDD": {
        "error": 2.7620374383305826e-06, 
        "filter_outliers_dict": {
            "filter_outliers": true, 
            "iterations": 1, 
            "std_devs": 10
        }, 
        "fit": "average", 
        "value": 9.876249632044467e-06
    }, 
    "H1": {
        "error": 0.002814509400687458, 
        "filter_outliers_dict": {
            "filter_outliers": true, 
            "iterations": 1, 
            "std_devs": 2
        }, 
        "fit": "average", 
        "value": -0.039546921315073175
    }, 
    "H2": {
        "error": 0.0025703256905924674, 
        "filter_outliers_dict": {
            "filter_outliers": true, 
            "iterations": 1, 
            "std_devs": 2
        }, 
        "fit": "average", 
        "value": -0.17990860507521136
    }, 
    "L1": {
        "error": 0.0017646005559918442, 
        "filter_outliers_dict": {
            "filter_outliers": true, 
            "iterations": 1, 
            "std_devs": 2
        }, 
        "fit": "average", 
        "value": -0.0243332289113149
    }, 
    "L2": {
        "error": 0.003150871639721829, 
        "filter_outliers_dict": {
            "filter_outliers": true, 
            "iterations": 1, 
            "std_devs": 2
        }, 
        "fit": "average", 
        "value": -0.01709454205211996
    }
}