{
    "AX": {
        "error": 0.004233645666452913,
        "filter_outliers_dict": {
            "filter_outliers": true,
            "iterations": 1,
            "std_devs": 2
        },
        "fit": "Average",
        "fn": 170,
        "include_baseline_error": false,
        "n": 180,
        "reviewed": true,
        "value": -0.046591148005545084
    },
    "CDD": {
        "error": 4.15276159165502e-06,
        "filter_outliers_dict": {
            "filter_outliers": true,
            "iterations": 1,
            "std_devs": 10
        },
        "fit": "Average",
        "fn": 180,
        "include_baseline_error": false,
        "n": 180,
        "reviewed": true,
        "value": 2.049088733555335e-05
    },
    "H1": {
        "error": 0.0029867293803342754,
        "filter_outliers_dict": {
            "filter_outliers": true,
            "iterations": 1,
            "std_devs": 2
        },
        "fit": "Average",
        "fn": 174,
        "include_baseline_error": false,
        "n": 180,
        "reviewed": true,
        "value": -0.02938430341341648
    },
    "H2": {
        "error": 0.0031665274184493686,
        "filter_outliers_dict": {
            "filter_outliers": true,
            "iterations": 1,
            "std_devs": 2
        },
        "fit": "average",
        "value": -0.17310857189998477
    },
    "L1": {
        "error": 0.0014282213411667844,
        "filter_outliers_dict": {
            "filter_outliers": true,
            "iterations": 1,
            "std_devs": 2
        },
        "fit": "Average",
        "fn": 169,
        "include_baseline_error": false,
        "n": 180,
        "reviewed": true,
        "value": -0.02310471239977808
    },
    "L2": {
        "error": 0.0041831988404041065,
        "filter_outliers_dict": {
            "filter_outliers": true,
            "iterations": 1,
            "std_devs": 2
        },
        "fit": "Average",
        "fn": 174,
        "include_baseline_error": false,
        "n": 180,
        "reviewed": true,
        "value": -0.01768927182768065
    }
}