{
    "AX": {
        "error": 0.004006686710768606,
        "filter_outliers_dict": {
            "filter_outliers": true,
            "iterations": 1,
            "std_devs": 2
        },
        "fit": "Average",
        "fn": 173,
        "include_baseline_error": false,
        "n": 180,
        "reviewed": true,
        "value": -0.0379290882992791
    },
    "CDD": {
        "error": 3.047767565296774e-06,
        "filter_outliers_dict": {
            "filter_outliers": true,
            "iterations": 1,
            "std_devs": 10
        },
        "fit": "Average",
        "fn": 180,
        "include_baseline_error": false,
        "n": 180,
        "reviewed": true,
        "value": 1.2294532401332011e-05
    },
    "H1": {
        "error": 0.002855401938693288,
        "filter_outliers_dict": {
            "filter_outliers": true,
            "iterations": 1,
            "std_devs": 2
        },
        "fit": "Average",
        "fn": 169,
        "include_baseline_error": false,
        "n": 180,
        "reviewed": true,
        "value": -0.0329821558118497
    },
    "H2": {
        "error": 0.0034213538046880686,
        "filter_outliers_dict": {
            "filter_outliers": true,
            "iterations": 1,
            "std_devs": 2
        },
        "fit": "average",
        "value": -0.17552235120895734
    },
    "L1": {
        "error": 0.001728426830695638,
        "filter_outliers_dict": {
            "filter_outliers": true,
            "iterations": 1,
            "std_devs": 2
        },
        "fit": "Average",
        "fn": 173,
        "include_baseline_error": false,
        "n": 180,
        "reviewed": true,
        "value": -0.019492566072943248
    },
    "L2": {
        "error": 0.00339758130381993,
        "filter_outliers_dict": {
            "filter_outliers": true,
            "iterations": 1,
            "std_devs": 2
        },
        "fit": "Average",
        "fn": 171,
        "include_baseline_error": false,
        "n": 180,
        "reviewed": true,
        "value": -0.016066576045807125
    }
}